{"AL":{"evs":9,"dem":795696,"gop":1255925},"AK":{"evs":3,"dem":122640,"gop":164676},"AZ":{"evs":11,"dem":1025232,"gop":1233654},"AR":{"evs":6,"dem":394409,"gop":647744},"CA":{"evs":55,"dem":7854285,"gop":4839958},"CO":{"evs":9,"dem":1323102,"gop":1185243},"CT":{"evs":7,"dem":905083,"gop":634892},"DE":{"evs":3,"dem":242584,"gop":165484},"DC":{"evs":3,"dem":267070,"gop":21381},"FL":{"evs":29,"dem":4237756,"gop":4163447},"GA":{"evs":16,"dem":1773827,"gop":2078688},"HI":{"evs":4,"dem":306658,"gop":121015},"ID":{"evs":4,"dem":212787,"gop":420911},"IL":{"evs":20,"dem":3019512,"gop":2135216},"IN":{"evs":11,"dem":1152887,"gop":1420543},"IA":{"evs":6,"dem":822544,"gop":730617},"KS":{"evs":6,"dem":440726,"gop":692634},"KY":{"evs":8,"dem":679370,"gop":1087190},"LA":{"evs":8,"dem":809141,"gop":1152262},"ME\u2013a\/l":{"evs":2,"dem":401306,"gop":292276},"MD":{"evs":10,"dem":1677844,"gop":971869},"MA":{"evs":11,"dem":1921290,"gop":1188314},"MI":{"evs":16,"dem":2564569,"gop":2115256},"MN":{"evs":10,"dem":1546167,"gop":1320225},"MS":{"evs":6,"dem":562949,"gop":710746},"MO":{"evs":10,"dem":1223796,"gop":1482440},"MT":{"evs":3,"dem":201839,"gop":267928},"NE\u2013a\/l":{"evs":2,"dem":302081,"gop":475064},"NV":{"evs":6,"dem":531373,"gop":463567},"NH":{"evs":4,"dem":369561,"gop":329918},"NJ":{"evs":14,"dem":2125101,"gop":1477568},"NM":{"evs":5,"dem":415335,"gop":335788},"NY":{"evs":29,"dem":4485741,"gop":2490431},"NC":{"evs":15,"dem":2178391,"gop":2270395},"ND":{"evs":3,"dem":124827,"gop":188163},"OH":{"evs":18,"dem":2827709,"gop":2661437},"OK":{"evs":7,"dem":443547,"gop":891325},"OR":{"evs":7,"dem":970488,"gop":754175},"PA":{"evs":20,"dem":2990274,"gop":2680434},"RI":{"evs":4,"dem":279677,"gop":157204},"SC":{"evs":9,"dem":865941,"gop":1071645},"SD":{"evs":3,"dem":145039,"gop":210610},"TN":{"evs":11,"dem":960709,"gop":1462330},"TX":{"evs":38,"dem":3308124,"gop":4569843},"UT":{"evs":6,"dem":251813,"gop":740600},"VT":{"evs":3,"dem":199239,"gop":92698},"VA":{"evs":13,"dem":1971820,"gop":1822522},"WA":{"evs":12,"dem":1755396,"gop":1290670},"WV":{"evs":5,"dem":238269,"gop":417655},"WI":{"evs":10,"dem":1620985,"gop":1407966},"WY":{"evs":3,"dem":69286,"gop":170962}}